README.md
setup.py
slackr/__init__.py
slackr/connection.py
slackr/eventhandler.py
slackr.egg-info/PKG-INFO
slackr.egg-info/SOURCES.txt
slackr.egg-info/dependency_links.txt
slackr.egg-info/requires.txt
slackr.egg-info/top_level.txt