Metadata-Version: 1.2
Name: slackr
Version: 0.1
Summary: An app for slackrs
Home-page: UNKNOWN
Author: UNKNOWN
Author-email: UNKNOWN
License: UNKNOWN
Platform: UNKNOWN
Requires-Python: >=2.6, !=3.0.*, !=3.1.*, !=3.2.*, <4
